{"9XM.in": [{"title": "9\u090f\u0915\u094d\u0938\u090f\u092e \u0936\u093e\u092f\u0930\u093f\u091c\u094d\u092e", "desc": "A comprehensive compilation of soothing and melodious songs performed by popular artists and musicians is played back-to-back.", "start": "20260701200000", "stop": "20260701203000"}, {"title": "9\u090f\u0915\u094d\u0938\u090f\u092e \u0936\u093e\u092f\u0930\u093f\u091c\u094d\u092e", "desc": "A comprehensive compilation of soothing and melodious songs performed by popular artists and musicians is played back-to-back.", "start": "20260701203000", "stop": "20260701210000"}, {"title": "9\u090f\u0915\u094d\u0938\u090f\u092e \u092e\u094d\u092f\u0942\u091c\u093f\u0915 \u0907\u0927\u0930 \u0939\u0948", "desc": "A comprehensive compilation of some of the hit songs composed by renowned artists and musicians is played back-to-back along with some popular jokes.", "start": "20260701210000", "stop": "20260701211500"}, {"title": "9\u090f\u0915\u094d\u0938\u090f\u092e \u092e\u094d\u092f\u0942\u091c\u093f\u0915 \u0907\u0927\u0930 \u0939\u0948", "desc": "A comprehensive compilation of some of the hit songs composed by renowned artists and musicians is played back-to-back along with some popular jokes.", "start": "20260701211500", "stop": "20260701213000"}, {"title": "9\u090f\u0915\u094d\u0938\u090f\u092e \u092e\u094d\u092f\u0942\u091c\u093f\u0915 \u0907\u0927\u0930 \u0939\u0948", "desc": "A comprehensive compilation of some of the hit songs composed by renowned artists and musicians is played back-to-back along with some popular jokes.", "start": "20260701213000", "stop": "20260701220000"}, {"title": "9\u090f\u0915\u094d\u0938\u090f\u092e \u092e\u094d\u092f\u0942\u091c\u093f\u0915 \u0907\u0927\u0930 \u0939\u0948", "desc": "A comprehensive compilation of some of the hit songs composed by renowned artists and musicians is played back-to-back along with some popular jokes.", "start": "20260701220000", "stop": "20260701223000"}, {"title": "9\u090f\u0915\u094d\u0938\u090f\u092e \u092e\u094d\u092f\u0942\u091c\u093f\u0915 \u0907\u0927\u0930 \u0939\u0948", "desc": "A comprehensive compilation of some of the hit songs composed by renowned artists and musicians is played back-to-back along with some popular jokes.", "start": "20260701223000", "stop": "20260701230000"}, {"title": "9\u090f\u0915\u094d\u0938\u090f\u092e \u092e\u094d\u092f\u0942\u091c\u093f\u0915 \u0907\u0927\u0930 \u0939\u0948", "desc": "A comprehensive compilation of some of the hit songs composed by renowned artists and musicians is played back-to-back along with some popular jokes.", "start": "20260701230000", "stop": "20260701233000"}, {"title": "9\u090f\u0915\u094d\u0938\u090f\u092e \u092e\u094d\u092f\u0942\u091c\u093f\u0915 \u0907\u0927\u0930 \u0939\u0948", "desc": "A comprehensive compilation of some of the hit songs composed by renowned artists and musicians is played back-to-back along with some popular jokes.", "start": "20260701233000", "stop": "20260701235959"}, {"title": "9\u090f\u0915\u094d\u0938\u090f\u092e \u0930\u093e\u0924 \u092d\u093e\u0930", "desc": "A compilation of some of the most popular Hindi songs by famous recording artists, played in succession for everyone to enjoy.", "start": "20260702000000", "stop": "20260702003000"}, {"title": "9XM Music Idhar Hai", "desc": "A comprehensive compilation of some of the hit songs composed by renowned artists and musicians is played back-to-back along with some popular jokes.", "start": "20260701210000", "stop": "20260701211500"}, {"title": "9XM Music Idhar Hai", "desc": "A comprehensive compilation of some of the hit songs composed by renowned artists and musicians is played back-to-back along with some popular jokes.", "start": "20260701211500", "stop": "20260701213000"}, {"title": "9XM Music Idhar Hai", "desc": "A comprehensive compilation of some of the hit songs composed by renowned artists and musicians is played back-to-back along with some popular jokes.", "start": "20260701213000", "stop": "20260701220000"}, {"title": "9XM Music Idhar Hai", "desc": "A comprehensive compilation of some of the hit songs composed by renowned artists and musicians is played back-to-back along with some popular jokes.", "start": "20260701220000", "stop": "20260701223000"}, {"title": "9XM Music Idhar Hai", "desc": "A comprehensive compilation of some of the hit songs composed by renowned artists and musicians is played back-to-back along with some popular jokes.", "start": "20260701223000", "stop": "20260701230000"}, {"title": "9XM Music Idhar Hai", "desc": "A comprehensive compilation of some of the hit songs composed by renowned artists and musicians is played back-to-back along with some popular jokes.", "start": "20260701230000", "stop": "20260701233000"}, {"title": "9XM Music Idhar Hai", "desc": "A comprehensive compilation of some of the hit songs composed by renowned artists and musicians is played back-to-back along with some popular jokes.", "start": "20260701233000", "stop": "20260702000000"}, {"title": "9xm Raat Bhar", "desc": "A compilation of some of the most popular Hindi songs by famous recording artists, played in succession for everyone to enjoy.", "start": "20260702000000", "stop": "20260702003000"}], "Nicktoons.uk": [{"title": "The Loud House", "desc": "Leni and her friends start hanging out at Gus's in 'Grub Snub', then in 'She's All Bat', Lucy gets jealous of Lola's newfound attention after she joins the Mortician's Club.", "start": "20260701200000", "stop": "20260701203100"}, {"title": "The Loud House", "desc": "Lincoln seeks a better seat in class in 'Musical Chairs', then in 'The Taunting Hour', Lynn gets heckled at her soccer game, and the Louds realize they all have critics.", "start": "20260701203100", "stop": "20260701210000"}, {"title": "The Loud House", "desc": "Lincoln and Clyde overwater Howard's rare orchid in 'The Orchid Grief', and in 'Forks and Knives Out', Lynn Sr. is stoked to compete on a cooking show until he learns he's up against Rosa.", "start": "20260701210000", "stop": "20260701213100"}, {"title": "The Loud House", "desc": "Vanzilla seems too broken down to ever drive again in 'Leave No Van Behind', then in 'Sponsor Tripped', Lynn and friends enjoy free perks around Royal Woods when their team gets sponsored.", "start": "20260701213100", "stop": "20260701220000"}, {"title": "The Loud House", "desc": "The Louds are invited to stay in a spooky castle in 'A Bite of Transylvania', then in 'Greece is the Word', during a tour of the Parthenon, Lincoln gets sent back to Ancient Greece.", "start": "20260701220000", "stop": "20260701223100"}, {"title": "The Loud House", "desc": "Stella uses Principal Ramirez's pool in 'Swimming Fools', then in 'Stage Combat', Luna and Luan compete for a grant.", "start": "20260701223100", "stop": "20260701230000"}, {"title": "The Loud House", "desc": "After Lola gets sick and can't compete in her pageant, Lincoln coaches Lana to take her place in 'Toads and Tiaras', then in 'Two Boys and a Baby', Lincoln and Clyde take on babysitting.", "start": "20260701230000", "stop": "20260701233000"}, {"title": "The Loud House", "desc": "Lincoln's social standing is at stake when Lisa gets put into his 5th grade class in 'Making the Grade', then in 'Vantastic Voyage', the kids try and trick Dad into buying a cool new van.", "start": "20260701233000", "stop": "20260702000000"}, {"title": "The Loud House", "desc": "The family takes a reading challenge in 'Read Aloud', then in 'Not a Loud', Lincoln discovers that the first page of his baby book is blank, and worries his parents are hiding something.", "start": "20260702000000", "stop": "20260702002500"}]}